rocket/__init__.py
rocket/rocket.py
nafissa-0.1.dist-info/METADATA
nafissa-0.1.dist-info/WHEEL
nafissa-0.1.dist-info/top_level.txt
nafissa-0.1.dist-info/RECORD
