Metadata-Version: 2.4
Name: nafissa
Version: 0.1
Summary: Mon package rocket
Author: sirine
License: MIT
Dynamic: author
Dynamic: license
Dynamic: summary
